easyab
