Metadata-Version: 1.0
Name: easyab
Version: 0.1.4
Summary: An A/B Testing framework
Home-page: UNKNOWN
Author: easyab
Author-email: easyab@bainainfo.com
License: BSD
Keywords: a/b testing
Platform: UNKNOWN
